childes_processor/__init__.py
childes_processor/main.py
childes_processor/src/__init__.py
childes_processor/src/default_g2p_config.json
childes_processor/src/dicts.py
childes_processor/src/downloader.py
childes_processor/src/processor.py
childes_processor-0.1.0.dist-info/licenses/LICENSE
childes_processor-0.1.0.dist-info/METADATA
childes_processor-0.1.0.dist-info/WHEEL
childes_processor-0.1.0.dist-info/entry_points.txt
childes_processor-0.1.0.dist-info/top_level.txt
childes_processor-0.1.0.dist-info/RECORD
