Metadata-Version: 2.4
Name: childes_processor
Version: 0.1.0
Summary: Library for downloading CHILDES, preprocessing it, and extracting phonetic transcriptions
Author-email: Zebulon Goriely <zebulon.goriely@cl.cam.ac.uk>
License: MIT License
Project-URL: Homepage, https://github.com/codebyzeb/ipa-childes
Project-URL: Issues, https://github.com/codebyzeb/ipa-childes/issues
Keywords: CHILDES,phonology,phonetics,linguistics,phone
Classifier: Development Status :: 1 - Planning
Classifier: Intended Audience :: Science/Research
Classifier: Operating System :: OS Independent
Classifier: Programming Language :: Python :: 3
Requires-Python: >=3.8
License-File: LICENSE
Requires-Dist: childespy>=1.0.0
Requires-Dist: g2p_plus>=0.1.3
Dynamic: license-file
